DLTA_AI_app/__main__.py
DLTA_AI_app/__main__.spec
DLTA_AI_app/inferencing.py
DLTA_AI_app/saved_models.json
DLTA_AI_app/setup.py
DLTA_AI_app/tempCodeRunnerFile.py
DLTA_AI_app/labelme/__init__.py
DLTA_AI_app/labelme/app.py
DLTA_AI_app/labelme/intelligence.py
DLTA_AI_app/labelme/label_file.py
DLTA_AI_app/labelme/logger.py
DLTA_AI_app/labelme/shape.py
DLTA_AI_app/labelme/testing.py
DLTA_AI_app/labelme/cli/__init__.py
DLTA_AI_app/labelme/cli/draw_json.py
DLTA_AI_app/labelme/cli/draw_label_png.py
DLTA_AI_app/labelme/cli/json_to_dataset.py
DLTA_AI_app/labelme/cli/on_docker.py
DLTA_AI_app/labelme/config/__init__.py
DLTA_AI_app/labelme/config/default_config.yaml
DLTA_AI_app/labelme/config/default_config_base.yaml
DLTA_AI_app/labelme/icons/SAM.png
DLTA_AI_app/labelme/icons/UI.png
DLTA_AI_app/labelme/icons/add.png
DLTA_AI_app/labelme/icons/add_point.png
DLTA_AI_app/labelme/icons/auto-img.png
DLTA_AI_app/labelme/icons/bbox.png
DLTA_AI_app/labelme/icons/brain.png
DLTA_AI_app/labelme/icons/cartesian.png
DLTA_AI_app/labelme/icons/checklist.png
DLTA_AI_app/labelme/icons/clear.png
DLTA_AI_app/labelme/icons/close.png
DLTA_AI_app/labelme/icons/color-line.png
DLTA_AI_app/labelme/icons/color.png
DLTA_AI_app/labelme/icons/copy.png
DLTA_AI_app/labelme/icons/dark-img.png
DLTA_AI_app/labelme/icons/delete.png
DLTA_AI_app/labelme/icons/done.png
DLTA_AI_app/labelme/icons/done.svg
DLTA_AI_app/labelme/icons/downloads.png
DLTA_AI_app/labelme/icons/edit.png
DLTA_AI_app/labelme/icons/expert.png
DLTA_AI_app/labelme/icons/export.png
DLTA_AI_app/labelme/icons/eye.png
DLTA_AI_app/labelme/icons/feBlend-icon.png
DLTA_AI_app/labelme/icons/feedback.png
DLTA_AI_app/labelme/icons/file.png
DLTA_AI_app/labelme/icons/fit-width.png
DLTA_AI_app/labelme/icons/fit-window.png
DLTA_AI_app/labelme/icons/fit.png
DLTA_AI_app/labelme/icons/frames.png
DLTA_AI_app/labelme/icons/github.png
DLTA_AI_app/labelme/icons/guide.png
DLTA_AI_app/labelme/icons/help.png
DLTA_AI_app/labelme/icons/icon.ico
DLTA_AI-1.1.dist-info/LICENSE
DLTA_AI-1.1.dist-info/METADATA
DLTA_AI-1.1.dist-info/WHEEL
DLTA_AI-1.1.dist-info/entry_points.txt
DLTA_AI-1.1.dist-info/top_level.txt
DLTA_AI-1.1.dist-info/RECORD
