Metadata-Version: 2.1
Name: DLTA-AI
Version: 1.1
Summary: DLTA-AI is the next generation of annotation tools, integrating the power of Computer Vision SOTA models to Labelme in a seamless expirence and intuitive workflow to make creating image datasets easier than ever before
Home-page: https://github.com/0ssamaak0/DLTA-AI
Author: 0ssamaak0
Author-email: 0ssamaak0@gmail.com
License: GPLv3
Requires-Python: >=3.8
License-File: LICENSE
Requires-Dist: PyQt5 (==5.15.9)
Requires-Dist: QtPy (==2.3.1)
Requires-Dist: termcolor (==2.2.0)
Requires-Dist: imgviz (==1.7.2)
Requires-Dist: opencv-python (==4.7.0.72)
Requires-Dist: pyqtdarktheme (==2.1.0)
Requires-Dist: supervision (==0.3.2)
Requires-Dist: gdown (==4.7.1)
Requires-Dist: ultralytics (==8.0.61)
Requires-Dist: onemetric (==0.1.2)
Requires-Dist: easydict (==1.10)
Requires-Dist: openmim (==0.3.2)
Requires-Dist: mmdet (==2.25.2)
Requires-Dist: scikit-image (==0.20.0)
Requires-Dist: filterpy (==1.4.5)
Requires-Dist: segment-anything (==1.0)
Requires-Dist: lap (==0.4.0)
Requires-Dist: orjson (==3.8.12)
Requires-Dist: notify-py (==0.3.42)
Requires-Dist: psutil (==5.9.4)
